deeplabcutcore/__init__.py
deeplabcutcore/pose_cfg.yaml
deeplabcutcore/version.py
deeplabcutcore/create_project/__init__.py
deeplabcutcore/create_project/add.py
deeplabcutcore/create_project/demo_data.py
deeplabcutcore/create_project/modelzoo.py
deeplabcutcore/create_project/new.py
deeplabcutcore/create_project/new_3d.py
deeplabcutcore/generate_training_dataset/__init__.py
deeplabcutcore/generate_training_dataset/frame_extraction.py
deeplabcutcore/generate_training_dataset/trainingsetmanipulation.py
deeplabcutcore/pose_estimation_3d/__init__.py
deeplabcutcore/pose_estimation_3d/camera_calibration.py
deeplabcutcore/pose_estimation_3d/plotting3D.py
deeplabcutcore/pose_estimation_3d/triangulation.py
deeplabcutcore/pose_estimation_tensorflow/__init__.py
deeplabcutcore/pose_estimation_tensorflow/config.py
deeplabcutcore/pose_estimation_tensorflow/default_config.py
deeplabcutcore/pose_estimation_tensorflow/evaluate.py
deeplabcutcore/pose_estimation_tensorflow/export.py
deeplabcutcore/pose_estimation_tensorflow/predict_videos.py
deeplabcutcore/pose_estimation_tensorflow/test.py
deeplabcutcore/pose_estimation_tensorflow/train.py
deeplabcutcore/pose_estimation_tensorflow/training.py
deeplabcutcore/pose_estimation_tensorflow/dataset/__init__.py
deeplabcutcore/pose_estimation_tensorflow/dataset/factory.py
deeplabcutcore/pose_estimation_tensorflow/dataset/pose_dataset.py
deeplabcutcore/pose_estimation_tensorflow/dataset/pose_dataset_deterministic.py
deeplabcutcore/pose_estimation_tensorflow/dataset/pose_dataset_imgaug.py
deeplabcutcore/pose_estimation_tensorflow/dataset/pose_dataset_tensorpack.py
deeplabcutcore/pose_estimation_tensorflow/dataset/pose_defaultdataset.py
deeplabcutcore/pose_estimation_tensorflow/models/__init__.py
deeplabcutcore/pose_estimation_tensorflow/models/pretrained/__init__.py
deeplabcutcore/pose_estimation_tensorflow/models/pretrained/download.sh
deeplabcutcore/pose_estimation_tensorflow/models/pretrained/pretrained_model_urls.yaml
deeplabcutcore-0.1.dist-info/AUTHORS
deeplabcutcore-0.1.dist-info/LICENSE
deeplabcutcore-0.1.dist-info/METADATA
deeplabcutcore-0.1.dist-info/WHEEL
deeplabcutcore-0.1.dist-info/top_level.txt
deeplabcutcore-0.1.dist-info/RECORD
